icnsutil/ArgbImage.py
icnsutil/IcnsFile.py
icnsutil/IcnsType.py
icnsutil/PackBytes.py
icnsutil/RawData.py
icnsutil/__init__.py
icnsutil/__main__.py
icnsutil/cli.py
icnsutil/autosize/ImageResizer.py
icnsutil/autosize/PixelResizer.py
icnsutil/autosize/SVGResizer.py
icnsutil/autosize/__init__.py
icnsutil/autosize/__main__.py
icnsutil/autosize/cli.py
icnsutil/autosize/helper.py
icnsutil-1.1.0.dist-info/LICENSE
icnsutil-1.1.0.dist-info/METADATA
icnsutil-1.1.0.dist-info/WHEEL
icnsutil-1.1.0.dist-info/entry_points.txt
icnsutil-1.1.0.dist-info/top_level.txt
icnsutil-1.1.0.dist-info/RECORD
